dcu/__init__.py
dcu/active_memory/__init__.py
dcu/active_memory/rotate.py
dcu/active_memory/upload.py
s3_backup_rotate-0.3.0.data/scripts/upload_rotate.py
s3_backup_rotate-0.3.0.dist-info/DESCRIPTION.rst
s3_backup_rotate-0.3.0.dist-info/METADATA
s3_backup_rotate-0.3.0.dist-info/RECORD
s3_backup_rotate-0.3.0.dist-info/WHEEL
s3_backup_rotate-0.3.0.dist-info/metadata.json
s3_backup_rotate-0.3.0.dist-info/top_level.txt
