Metadata-Version: 2.0
Name: s3-backup-rotate
Version: 0.3.0
Summary: Script to rotate backup files on AWS S3 according to a grandfather, father, son strategy.
Home-page: https://github.com/dirkcuys/s3-backup-rotate
Author: Dirk Uys
Author-email: dirkcuys@gmail.com
License: MIT
Platform: UNKNOWN
Requires-Dist: boto3 (>=1.0.0)
